odoo/addons/website_snippet_timeline/README.rst
odoo/addons/website_snippet_timeline/__init__.py
odoo/addons/website_snippet_timeline/__manifest__.py
odoo/addons/website_snippet_timeline/i18n/it.po
odoo/addons/website_snippet_timeline/i18n/website_snippet_timeline.pot
odoo/addons/website_snippet_timeline/readme/CONTRIBUTORS.rst
odoo/addons/website_snippet_timeline/readme/DESCRIPTION.rst
odoo/addons/website_snippet_timeline/readme/USAGE.rst
odoo/addons/website_snippet_timeline/static/description/icon.svg
odoo/addons/website_snippet_timeline/static/description/index.html
odoo/addons/website_snippet_timeline/static/src/js/options.js
odoo/addons/website_snippet_timeline/static/src/scss/000.scss
odoo/addons/website_snippet_timeline/templates/assets.xml
odoo/addons/website_snippet_timeline/templates/snippets.xml
odoo13_addon_website_snippet_timeline-13.0.1.0.1.dev5.dist-info/METADATA
odoo13_addon_website_snippet_timeline-13.0.1.0.1.dev5.dist-info/WHEEL
odoo13_addon_website_snippet_timeline-13.0.1.0.1.dev5.dist-info/top_level.txt
odoo13_addon_website_snippet_timeline-13.0.1.0.1.dev5.dist-info/RECORD
